{"chunk_definitions":[{"row":36,"row_count":1,"visible":true,"expansion_state":0,"options":{"engine":"r","label":"unnamed-chunk-7","dev":"png"},"document_id":"6996FC6A","chunk_id":"c4cxesuqtzfv8","chunk_label":"unnamed-chunk-2"},{"row":71,"row_count":1,"visible":true,"expansion_state":0,"options":{"engine":"r","label":"unnamed-chunk-10","dev":"png"},"document_id":"6996FC6A","chunk_id":"c1lb0mgtaukov","chunk_label":"unnamed-chunk-3"},{"row":77,"row_count":1,"visible":true,"expansion_state":0,"options":{"engine":"r","label":"unnamed-chunk-12","dev":"png"},"document_id":"6996FC6A","chunk_id":"cw229onexek73","chunk_label":"unnamed-chunk-4"},{"row":106,"row_count":1,"visible":true,"expansion_state":0,"options":{"engine":"r","label":"unnamed-chunk-17","dev":"png"},"document_id":"6996FC6A","chunk_id":"cbduuqnk0pvy3","chunk_label":"unnamed-chunk-5"},{"row":121,"row_count":1,"visible":true,"expansion_state":0,"options":{"engine":"r","label":"unnamed-chunk-15","dev":"png"},"document_id":"6996FC6A","chunk_id":"cv3u0f3e1v0fg","chunk_label":"unnamed-chunk-6"},{"row":127,"row_count":1,"visible":true,"expansion_state":0,"options":{"engine":"r","label":"unnamed-chunk-18","dev":"png"},"document_id":"6996FC6A","chunk_id":"c993h2gqrsiyn","chunk_label":"unnamed-chunk-7"},{"row":136,"row_count":1,"visible":true,"expansion_state":0,"options":{"engine":"r","label":"unnamed-chunk-19","dev":"png"},"document_id":"6996FC6A","chunk_id":"cnx364u63z4ep","chunk_label":"unnamed-chunk-8"},{"row":149,"row_count":1,"visible":true,"expansion_state":0,"options":{"engine":"r","label":"unnamed-chunk-20","dev":"png"},"document_id":"6996FC6A","chunk_id":"crquixiwgtf9i","chunk_label":"unnamed-chunk-9"},{"row":168,"row_count":1,"visible":true,"expansion_state":0,"options":{"engine":"r","label":"unnamed-chunk-21","dev":"png"},"document_id":"6996FC6A","chunk_id":"cj6o6oj7tku0g","chunk_label":"unnamed-chunk-10"},{"row":25,"row_count":1,"visible":true,"expansion_state":0,"options":{"engine":"r","label":"unnamed-chunk-16","dev":"png"},"document_id":"6996FC6A","chunk_id":"cn9thlpfglqyk","chunk_label":"unnamed-chunk-1"}],"doc_write_time":1742581381,"chunk_rendered_width":662}